{"enc_704212.png": "1234", "enc_55d02a.png": "1234", "enc_5ad86a.wav": "2244", "enc_5b1726.wav": "2244", "enc_8cf8cb.wav": "2244", "enc_3b8aa8.wav": "2244", "enc_5d61f6.wav": "2244", "enc_cebeea.avi": "8989", "enc_d12529.avi": "8989", "enc_2a3e06.png": "happy", "enc_c30a2b.png": "happy", "enc_7c0ec2.png": "happy", "enc_24065e.wav": "happy", "enc_424d2d.avi": "happy", "enc_bfff12.avi": "happy", "enc_de09ea.png": "happy", "enc_4a9e15.wav": "happy", "enc_322ed9.png": "happy", "enc_27314a.png": "fast", "enc_adc156.wav": "happy", "enc_26643b.avi": "motion", "enc_e6d160.avi": "motion", "enc_ee7cd3.png": "happy", "enc_8a6e65.png": "happy", "enc_9b3fa2.png": "happy", "enc_239e59.png": "happy", "enc_2f7149.png": "fast", "enc_3200c7.png": "happy", "enc_d22e3d.png": "fast", "enc_0e0c6b.png": "fast", "enc_7c39ee.png": "happy", "enc_b614a5.png": "motion", "enc_268020.png": "motion", "enc_edb8d0.png": "motion", "enc_582615.png": "motion", "enc_f92e94.png": "motion", "enc_77610e.png": "happy", "enc_92059f.avi": "happy", "enc_56d524.avi": "happy", "enc_2efa5f.avi": "happy", "enc_6986ad.avi": "fast", "enc_feca51.avi": "fast", "enc_6c91f2.avi": "fast", "enc_ca5c10.avi": "fast", "enc_e3f23a.avi": "fast", "enc_c5578d.avi": "fast", "enc_f87c70.avi": "motion", "enc_a69f46.avi": "fast"}